gi-stubs/__init__.pyi
gi-stubs/__multi_version_stubs/Gtk3.pyi
gi-stubs/__multi_version_stubs/Soup2.pyi
gi-stubs/repository/AppIndicator3.pyi
gi-stubs/repository/Atk.pyi
gi-stubs/repository/AyatanaAppIndicator3.pyi
gi-stubs/repository/Farstream.pyi
gi-stubs/repository/GIRepository.pyi
gi-stubs/repository/GLib.pyi
gi-stubs/repository/GModule.pyi
gi-stubs/repository/GObject.pyi
gi-stubs/repository/GSound.pyi
gi-stubs/repository/Gdk.pyi
gi-stubs/repository/GdkPixbuf.pyi
gi-stubs/repository/Geoclue.pyi
gi-stubs/repository/Gio.pyi
gi-stubs/repository/Gspell.pyi
gi-stubs/repository/Gst.pyi
gi-stubs/repository/GstPbutils.pyi
gi-stubs/repository/Gtk.pyi
gi-stubs/repository/GtkSource.pyi
gi-stubs/repository/Pango.pyi
gi-stubs/repository/PangoCairo.pyi
gi-stubs/repository/Soup.pyi
gi-stubs/repository/__init__.pyi
PyGObject_stubs-2.1.0.dist-info/LICENSE
PyGObject_stubs-2.1.0.dist-info/METADATA
PyGObject_stubs-2.1.0.dist-info/WHEEL
PyGObject_stubs-2.1.0.dist-info/top_level.txt
PyGObject_stubs-2.1.0.dist-info/RECORD
