Metadata-Version: 2.1
Name: PyGObject-stubs
Version: 2.1.0
Summary: Typing stubs for PyGObject
Author: Christoph Reiter
Author-email: reiter.christoph@gmail.com
License: LGPL-2.1
Project-URL: homepage, https://github.com/pygobject/pygobject-stubs
Project-URL: repository, https://github.com/pygobject/pygobject-stubs
Classifier: Programming Language :: Python :: 3
Classifier: Intended Audience :: Developers
Classifier: License :: OSI Approved :: GNU Lesser General Public License v2 or later (LGPLv2+)
Classifier: Operating System :: OS Independent
Requires-Python: >=3.7
Provides-Extra: dev
License-File: LICENSE
